idade_calculator/__init__.py
idade_calculator/idade.py
idade_calculator-0.0.1.dist-info/METADATA
idade_calculator-0.0.1.dist-info/WHEEL
idade_calculator-0.0.1.dist-info/top_level.txt
idade_calculator-0.0.1.dist-info/RECORD
