Metadata-Version: 2.4
Name: idade_calculator
Version: 0.0.1
Summary: Calculadora de Idade
Home-page: https://github.com/FabricianoGiovanelli/simple-package-template.git
Author: Fabriciano
Author-email: fgs85@live.com
Requires-Python: >=3.8
Dynamic: author
Dynamic: author-email
Dynamic: description
Dynamic: description-content-type
Dynamic: home-page
Dynamic: requires-python
Dynamic: summary
